<?xml version="1.0" encoding="utf-8"?>
<Defs>
  <PawnKindDef Name="MagmaFaction" Abstract="True">
    <defaultFactionType>MagmaEmpire</defaultFactionType>
    <chemicalAddictionChance>0</chemicalAddictionChance>
    <baseRecruitDifficulty>0.40</baseRecruitDifficulty>
    <backstoryCryptosleepCommonality>0</backstoryCryptosleepCommonality>
    <backstoryCategories>
      <li>Outlander</li>
    </backstoryCategories>
    <apparelTags>
      <li>IndustrialMilitaryBasic</li>
    </apparelTags>
  </PawnKindDef>
  <PawnKindDef Name="MagmaSoldierBase" ParentName="MagmaFaction">
    <defName>MagmaSoldier</defName>
    <label>Volcanian Fighter</label>
    <race>MagmaRace</race>
    <combatPower>25</combatPower>
    <itemQuality>Poor</itemQuality>
    <isFighter>true</isFighter>
    <maxGenerationAge>25</maxGenerationAge>
    <gearHealthRange>
      <min>0.5</min>
      <max>2</max>
    </gearHealthRange>
    <apparelMoney>
      <min>6000</min>
      <max>6000</max>
    </apparelMoney>
    <apparelAllowHeadgearChance>1</apparelAllowHeadgearChance>
    <weaponMoney>
      <min>2300</min>
      <max>2400</max>
    </weaponMoney>
    <weaponTags>
      <li>FluxRifleNormal</li>
    </weaponTags>
    <techHediffsMoney>
      <min>1000</min>
      <max>1800</max>
    </techHediffsMoney>
    <techHediffsTags>
      <li>Advanced</li>
    </techHediffsTags>
    <techHediffsChance>0.1</techHediffsChance>
    <invNutrition>2.55</invNutrition>
    <inventoryOptions>
      <skipChance>0.01</skipChance>
      <subOptionsChooseOne>
        <li>
          <thingDef>ZebraStyleMeat</thingDef>
          <countRange>
            <min>1</min>
            <max>5</max>
          </countRange>
        </li>
        <li>
          <thingDef>MedicineUltratech</thingDef>
          <countRange>
            <min>1</min>
            <max>1</max>
          </countRange>
        </li>
      </subOptionsChooseOne>
    </inventoryOptions>
  </PawnKindDef>
  <PawnKindDef ParentName="MagmaSoldierBase">
    <defName>MagmaSoldierNormal</defName>
    <label>Volcanian Soldier</label>
    <weaponMoney>
      <min>2300</min>
      <max>2400</max>
    </weaponMoney>
    <apparelRequired>
      <li>Apparel_BowlerHat</li>
      <li>Apparel_FlakJacket</li>
    </apparelRequired>
    <weaponTags>
      <li>FluxRifleNormal</li>
    </weaponTags>
    <combatPower>85</combatPower>
  </PawnKindDef>
  <PawnKindDef ParentName="MagmaSoldierBase">
    <defName>MagmaTrader</defName>
    <label>Volcanian Dominion Trader</label>
    <race>BlueMagmaRace</race>
    <combatPower>35</combatPower>
    <invNutrition>2.55</invNutrition>
    <invFoodDef>Pemmican</invFoodDef>
    <apparelTags>
      <li>IndustrialBasic</li>
    </apparelTags>
    <trader>true</trader>
    <apparelRequired Inherit="False">
      <li>Apparel_BasicShirt</li>
    </apparelRequired>
    <weaponMoney>
      <min>2300</min>
      <max>2400</max>
    </weaponMoney>
    <weaponTags>
      <li>FluxRifleBlue</li>
    </weaponTags>
  </PawnKindDef>
  <PawnKindDef ParentName="MagmaSoldierBase">
    <defName>MagmaTroop</defName>
    <label>Volcanian Troop</label>
    <weaponTags>
      <li>FluxRifleNormal</li>
    </weaponTags>
    <apparelMoney>
      <min>8070</min>
      <max>8070</max>
    </apparelMoney>
    <apparelRequired>
      <li>Apparel_FlakVest</li>
      <li>Apparel_AdvancedHelmet</li>
    </apparelRequired>
    <combatPower>95</combatPower>
  </PawnKindDef>
  <PawnKindDef ParentName="MagmaSoldierBase">
    <defName>MagmaCommando</defName>
    <label>Volcanian Official</label>
    <weaponTags>
      <li>FluxRifleNormal</li>
    </weaponTags>
    <apparelMoney>
      <min>8070</min>
      <max>8070</max>
    </apparelMoney>
    <apparelRequired>
      <li>Apparel_FlakVest</li>
      <li>Apparel_FlakJacket</li>
      <li>Apparel_AdvancedHelmet</li>
    </apparelRequired>
    <combatPower>95</combatPower>
  </PawnKindDef>
  <PawnKindDef>
    <defName>MagmaCommander</defName>
    <label>Volcanian Commander</label>
    <race>MagmaRace</race>
    <factionLeader>true</factionLeader>
    <combatPower>250</combatPower>
    <defaultFactionType>MagmaEmpire</defaultFactionType>
    <baseRecruitDifficulty>0.7</baseRecruitDifficulty>
    <backstoryCategories>
      <li>Outlander</li>
    </backstoryCategories>
    <invNutrition>2.55</invNutrition>
    <backstoryCryptosleepCommonality>0.2</backstoryCryptosleepCommonality>
    <maxGenerationAge>30</maxGenerationAge>
    <gearHealthRange>
      <min>1</min>
      <max>1</max>
    </gearHealthRange>
    <apparelTags>
      <li>IndustrialMilitaryAdvanced</li>
    </apparelTags>
    <apparelMoney>
      <min>9070</min>
      <max>9070</max>
    </apparelMoney>
    <apparelRequired>
      <li>Apparel_PlateArmor</li>
      <li>Apparel_AdvancedHelmet</li>
    </apparelRequired>
    <apparelAllowHeadgearChance>1</apparelAllowHeadgearChance>
    <weaponMoney>
      <min>2300</min>
      <max>2400</max>
    </weaponMoney>
    <weaponTags>
      <li>FluxRifleNormal</li>
    </weaponTags>
    <techHediffsMoney>
      <min>1000</min>
      <max>5000</max>
    </techHediffsMoney>
    <techHediffsTags>
      <li>Advanced</li>
    </techHediffsTags>
    <techHediffsChance>1</techHediffsChance>
    <inventoryOptions>
      <skipChance>0.01</skipChance>
      <subOptionsChooseOne>
        <li>
          <thingDef>RainbowMeat</thingDef>
          <countRange>
            <min>1</min>
            <max>5</max>
          </countRange>
        </li>
        <li>
          <thingDef>MedicineUltratech</thingDef>
          <countRange>
            <min>1</min>
            <max>1</max>
          </countRange>
        </li>
      </subOptionsChooseOne>
    </inventoryOptions>
  </PawnKindDef>
  <PawnKindDef>
    <defName>MagmaSpeeder</defName>
    <label>Volcanian General</label>
    <race>BlueMagmaRace</race>
    <factionLeader>false</factionLeader>
    <combatPower>150</combatPower>
    <defaultFactionType>MagmaEmpire</defaultFactionType>
    <baseRecruitDifficulty>0.7</baseRecruitDifficulty>
    <backstoryCategories>
      <li>Outlander</li>
    </backstoryCategories>
    <invNutrition>2.55</invNutrition>
    <backstoryCryptosleepCommonality>0.2</backstoryCryptosleepCommonality>
    <maxGenerationAge>30</maxGenerationAge>
    <gearHealthRange>
      <min>1</min>
      <max>1</max>
    </gearHealthRange>
    <apparelTags>
      <li>IndustrialMilitaryBasic</li>
    </apparelTags>
    <apparelMoney>
      <min>8000</min>
      <max>8000</max>
    </apparelMoney>
    <apparelRequired>
      <li>Apparel_PlateArmor</li>
    </apparelRequired>
    <apparelAllowHeadgearChance>0.2</apparelAllowHeadgearChance>
    <weaponMoney>
      <min>2300</min>
      <max>2400</max>
    </weaponMoney>
    <weaponTags>
      <li>FluxRifleBlue</li>
    </weaponTags>
    <techHediffsMoney>
      <min>1000</min>
      <max>5000</max>
    </techHediffsMoney>
    <techHediffsTags>
      <li>Advanced</li>
    </techHediffsTags>
    <techHediffsChance>1</techHediffsChance>
    <inventoryOptions>
      <skipChance>0.01</skipChance>
      <subOptionsChooseOne>
        <li>
          <thingDef>GlowingMeat</thingDef>
          <countRange>
            <min>1</min>
            <max>5</max>
          </countRange>
        </li>
        <li>
          <thingDef>MedicineUltratech</thingDef>
          <countRange>
            <min>1</min>
            <max>1</max>
          </countRange>
        </li>
      </subOptionsChooseOne>
    </inventoryOptions>
  </PawnKindDef>
</Defs>